README.rst
setup.py
bin/rafflepy
rafflepy/__init__.py
rafflepy/raffle.py
rafflepy.egg-info/PKG-INFO
rafflepy.egg-info/SOURCES.txt
rafflepy.egg-info/dependency_links.txt
rafflepy.egg-info/not-zip-safe
rafflepy.egg-info/pbr.json
rafflepy.egg-info/requires.txt
rafflepy.egg-info/top_level.txt