Metadata-Version: 1.1
Name: rafflepy
Version: 0.1.2
Summary: Randomly select a WINNER from a list of candidates.
Home-page: https://github.com/kejbaly2/rafflepy
Author: Chris Ward
Author-email: kejbaly2@gmail.com
License: GPLv3
Download-URL: https://github.com/kejbaly2/rafflepy/archive/master.zip
Keywords: random
Platform: UNKNOWN
Classifier: License :: OSI Approved :: GNU General Public License v3 (GPLv3)
Classifier: Natural Language :: English
Classifier: Programming Language :: Python :: 2.7
Classifier: Topic :: Office/Business
Classifier: Topic :: Utilities
Provides: rafflepy
